rds_migration/README.md
rds_migration/__init__.py
rds_migration/cli.py
rds_migration/config.py
rds_migration/connections.py
rds_migration/database.py
rds_migration/datadog.py
rds_migration/logger.py
rds_migration/materialized_views.py
rds_migration/migration.py
rds_migration/py.typed
rds_migration/validation.py
rds_migration_toolkit-1.0.1.dist-info/licenses/LICENSE
rds_migration_toolkit-1.0.1.dist-info/METADATA
rds_migration_toolkit-1.0.1.dist-info/WHEEL
rds_migration_toolkit-1.0.1.dist-info/entry_points.txt
rds_migration_toolkit-1.0.1.dist-info/top_level.txt
rds_migration_toolkit-1.0.1.dist-info/RECORD
