Metadata-Version: 2.4
Name: rds-migration-toolkit
Version: 1.0.1
Summary: Production-grade PostgreSQL database migration tool for AWS RDS with DataDog monitoring
Author-email: Arthur Mandel <arthur.mandel@external.freshrealm.com>
Maintainer-email: Arthur Mandel <arthur.mandel@external.freshrealm.com>
License:                                  Apache License
Project-URL: Homepage, https://github.com/arthur-mandel-freshRealm/openSourceTools
Project-URL: Repository, https://github.com/arthur-mandel-freshRealm/openSourceTools
Project-URL: Issues, https://github.com/arthur-mandel-freshRealm/openSourceTools/issues
Keywords: aws,rds,postgresql,database,migration,datadog,materialized-views,pg_dump,pg_restore
Classifier: Development Status :: 5 - Production/Stable
Classifier: Intended Audience :: Developers
Classifier: Intended Audience :: System Administrators
Classifier: License :: OSI Approved :: MIT License
Classifier: Operating System :: OS Independent
Classifier: Programming Language :: Python :: 3
Classifier: Programming Language :: Python :: 3.9
Classifier: Programming Language :: Python :: 3.10
Classifier: Programming Language :: Python :: 3.11
Classifier: Programming Language :: Python :: 3.12
Classifier: Topic :: Database
Classifier: Topic :: System :: Systems Administration
Classifier: Topic :: Software Development :: Libraries :: Python Modules
Classifier: Typing :: Typed
Requires-Python: >=3.9
License-File: LICENSE
Requires-Dist: boto3>=1.28.0
Requires-Dist: click>=8.1.0
Requires-Dist: datadog>=0.47.0
Requires-Dist: psycopg[binary]>=3.1.0
Requires-Dist: pydantic>=2.0.0
Requires-Dist: pydantic-settings>=2.0.0
Requires-Dist: rich>=13.0.0
Requires-Dist: structlog>=23.1.0
Provides-Extra: dev
Requires-Dist: pytest>=7.4.0; extra == "dev"
Requires-Dist: pytest-cov>=4.1.0; extra == "dev"
Requires-Dist: mypy>=1.5.0; extra == "dev"
Requires-Dist: ruff>=0.1.0; extra == "dev"
Requires-Dist: black>=23.9.0; extra == "dev"
Requires-Dist: types-boto3>=1.0.0; extra == "dev"
Provides-Extra: tracing
Requires-Dist: ddtrace>=2.0.0; extra == "tracing"
Dynamic: license-file
